pathstring.py
pathstring-1.1.0.dist-info/LICENSE.txt
pathstring-1.1.0.dist-info/WHEEL
pathstring-1.1.0.dist-info/METADATA
pathstring-1.1.0.dist-info/RECORD
