Metadata-Version: 2.1
Name: pathstring
Version: 1.1.0
Summary: String with path operations.
Keywords: path
Author-email: "H. Turgut Uyar" <uyar@tekir.org>
Requires-Python: ~=3.7
Classifier: Development Status :: 5 - Production/Stable
Classifier: Intended Audience :: Developers
Classifier: License :: OSI Approved :: BSD License
Classifier: Operating System :: OS Independent
Classifier: Programming Language :: Python
Classifier: Programming Language :: Python :: 3.10
Classifier: Programming Language :: Python :: 3.9
Classifier: Programming Language :: Python :: 3.8
Classifier: Programming Language :: Python :: 3.7
Classifier: Programming Language :: Python :: Implementation :: CPython
Classifier: Programming Language :: Python :: Implementation :: PyPy
Classifier: Topic :: Software Development :: Libraries :: Python Modules
Requires-Dist: pytest ; extra == "dev"
Requires-Dist: flake8 ; extra == "dev"
Requires-Dist: tox ; extra == "dev"
Project-URL: Homepage, https://pypi.org/project/pathstring/
Project-URL: Repository, https://github.com/uyar/pathstring
Provides-Extra: dev
